{"Names":{"0":"\ud83d\udc1f Ross Young","1":"\ud83c\udfc0 Mark Gurman","2":"\ud83d\udcc9 Trendforce","3":"\ud83c\udfa7 52audio","4":"\ud83d\udd58 9to5Mac","5":"\u2753 MacRumors","6":"\ud83c\udde8\ud83c\uddf3 China Times","7":"\ud83d\udc68\u200d\ud83d\udcbb Ming-Chi Kuo","8":"\ud83e\uddfb Jon Prosser","9":"\ud83c\udf4d Max Weinbach","10":"\ud83d\udd22 DigiTimes","11":"\ud83e\udded Macotakara","12":"\ud83e\udd85 Barclays","13":"\ud83d\udda5 Sonny Dickson","14":"\ud83d\udcf1 Jeff Pu","15":"\ud83c\udf33 Wedbush Securities"},"Accuracy":{"0":"92.9%","1":"86.4%","2":"84.5%","3":"83.3%","4":"82.8%","5":"72.7%","6":"72.7%","7":"72.5%","8":"69%","9":"69%","10":"62.5%","11":"58.5%","12":"55.6%","13":"54.5%","14":"50%","15":"45.4%"}}